TurbineClient-4.0.3.data/scripts/turbine_application_list
TurbineClient-4.0.3.data/scripts/turbine_consumer_list
TurbineClient-4.0.3.data/scripts/turbine_consumer_log
TurbineClient-4.0.3.data/scripts/turbine_job_script
TurbineClient-4.0.3.data/scripts/turbine_session_append
TurbineClient-4.0.3.data/scripts/turbine_session_create
TurbineClient-4.0.3.data/scripts/turbine_session_delete
TurbineClient-4.0.3.data/scripts/turbine_session_graphs
TurbineClient-4.0.3.data/scripts/turbine_session_kill
TurbineClient-4.0.3.data/scripts/turbine_session_list
TurbineClient-4.0.3.data/scripts/turbine_session_results
TurbineClient-4.0.3.data/scripts/turbine_session_start
TurbineClient-4.0.3.data/scripts/turbine_session_stats
TurbineClient-4.0.3.data/scripts/turbine_session_status
TurbineClient-4.0.3.data/scripts/turbine_session_stop
TurbineClient-4.0.3.data/scripts/turbine_simulation_create
TurbineClient-4.0.3.data/scripts/turbine_simulation_delete
TurbineClient-4.0.3.data/scripts/turbine_simulation_get
TurbineClient-4.0.3.data/scripts/turbine_simulation_list
TurbineClient-4.0.3.data/scripts/turbine_simulation_update
turbine/__init__.py
turbine/rpython.py
turbine/utility.py
turbine/version.py
turbine/commands/__init__.py
turbine/commands/requests_base.py
turbine/commands/turbine_application_script.py
turbine/commands/turbine_consumer_script.py
turbine/commands/turbine_csv_script.py
turbine/commands/turbine_csv_session_script.py
turbine/commands/turbine_job_script.py
turbine/commands/turbine_mongo_archiver.py
turbine/commands/turbine_psuade_script.py
turbine/commands/turbine_psuade_session_script.py
turbine/commands/turbine_session_result_script.py
turbine/commands/turbine_session_script.py
turbine/commands/turbine_simulation_script.py
TurbineClient-4.0.3.dist-info/LICENSE.md
TurbineClient-4.0.3.dist-info/METADATA
TurbineClient-4.0.3.dist-info/WHEEL
TurbineClient-4.0.3.dist-info/top_level.txt
TurbineClient-4.0.3.dist-info/RECORD
